AFTP/__init__.py
AFTP/Client/Bin/AFTPWarnings.py
AFTP/Client/Bin/errors.py
AFTP/Client/Bin/main.py
AFTP/Server/Bin/AFTPWarnings.py
AFTP/Server/Bin/errors.py
AFTP/Server/Bin/main.py
AFTP-0.0.3.dist-info/METADATA
AFTP-0.0.3.dist-info/WHEEL
AFTP-0.0.3.dist-info/top_level.txt
AFTP-0.0.3.dist-info/RECORD
