Metadata-Version: 2.1
Name: AFTP
Version: 0.0.3
Summary: A file trasfer protocol
Home-page: UNKNOWN
Author: Zelabs
Author-email: administration@zelabs.it
License: UNKNOWN
Keywords: python,file,protocol,safe,transfer
Platform: UNKNOWN
Classifier: Development Status :: 1 - Planning
Classifier: Intended Audience :: Developers
Classifier: Programming Language :: Python :: 3
Classifier: Operating System :: Unix
Classifier: Operating System :: MacOS :: MacOS X
Classifier: Operating System :: Microsoft :: Windows
Requires-Dist: cryptography
Requires-Dist: pycryptodome
